lesting.http-0.1.0-py3.9-nspkg.pth
lesting/http/__init__.py
lesting.http-0.1.0.dist-info/LICENSE
lesting.http-0.1.0.dist-info/METADATA
lesting.http-0.1.0.dist-info/WHEEL
lesting.http-0.1.0.dist-info/namespace_packages.txt
lesting.http-0.1.0.dist-info/top_level.txt
lesting.http-0.1.0.dist-info/RECORD
